pyelf2rel/__init__.py
pyelf2rel/__main__.py
pyelf2rel/elf.py
pyelf2rel/elf2rel.py
pyelf2rel/error.py
pyelf2rel/lst.py
pyelf2rel/makelst.py
pyelf2rel/rel.py
pyelf2rel/util.py
pyelf2rel-1.0.8.dist-info/METADATA
pyelf2rel-1.0.8.dist-info/WHEEL
pyelf2rel-1.0.8.dist-info/entry_points.txt
pyelf2rel-1.0.8.dist-info/licenses/LICENSE
pyelf2rel-1.0.8.dist-info/RECORD
