Metadata-Version: 2.3
Name: pyelf2rel
Version: 1.0.8
Summary: Python tools for creating Nintendo REL files
Project-URL: Documentation, https://github.com/SeekyCt/pyelf2rel#readme
Project-URL: Homepage, https://github.com/SeekyCt/pyelf2rel
Project-URL: Issues, https://github.com/SeekyCt/pyelf2rel/issues
Author: Seeky
License-Expression: MIT
License-File: LICENSE
Classifier: Development Status :: 4 - Beta
Classifier: License :: OSI Approved :: MIT License
Classifier: Operating System :: OS Independent
Classifier: Programming Language :: Python
Classifier: Programming Language :: Python :: 3.9
Classifier: Programming Language :: Python :: 3.10
Classifier: Programming Language :: Python :: 3.11
Classifier: Programming Language :: Python :: 3.12
Classifier: Programming Language :: Python :: 3.13
Classifier: Programming Language :: Python :: Implementation :: CPython
Classifier: Programming Language :: Python :: Implementation :: PyPy
Requires-Python: >=3.9
Requires-Dist: pyelftools
